OpenFisca_UK-0.34.1.data/data/share/openfisca/openfisca-country-template/CHANGELOG.md
OpenFisca_UK-0.34.1.data/data/share/openfisca/openfisca-country-template/LICENSE
OpenFisca_UK-0.34.1.data/data/share/openfisca/openfisca-country-template/README.md
openfisca_uk/__init__.py
openfisca_uk/api.py
openfisca_uk/entities.py
openfisca_uk/initial_setup.py
openfisca_uk/model_api.py
openfisca_uk/parameter_tree.py
openfisca_uk/repo.py
openfisca_uk/system.py
openfisca_uk/config/__init__.py
openfisca_uk/config/postcode_lookup.py
openfisca_uk/data/__init__.py
openfisca_uk/data/cli.py
openfisca_uk/data/datasets/__init__.py
openfisca_uk/data/datasets/frs/__init__.py
openfisca_uk/data/datasets/frs/frs.py
openfisca_uk/data/datasets/frs/raw_frs.py
openfisca_uk/data/datasets/frs/synth_frs.py
openfisca_uk/data/datasets/frs/enhanced/README.md
openfisca_uk/data/datasets/frs/enhanced/__init__.py
openfisca_uk/data/datasets/frs/enhanced/utils.py
openfisca_uk/data/datasets/frs/enhanced/stages/__init__.py
openfisca_uk/data/datasets/frs/enhanced/stages/baseline_variables.py
openfisca_uk/data/datasets/frs/enhanced/stages/remove_zero_weight_households.py
openfisca_uk/data/datasets/frs/enhanced/stages/calibration/__init__.py
openfisca_uk/data/datasets/frs/enhanced/stages/calibration/calibrate.py
openfisca_uk/data/datasets/frs/enhanced/stages/calibration/calibrated_frs.py
openfisca_uk/data/datasets/frs/enhanced/stages/calibration/monitor.py
openfisca_uk/data/datasets/frs/enhanced/stages/calibration/losses/__init__.py
openfisca_uk/data/datasets/frs/enhanced/stages/calibration/losses/loss_calculator.py
openfisca_uk/data/datasets/frs/enhanced/stages/calibration/losses/loss_category.py
openfisca_uk/data/datasets/frs/enhanced/stages/calibration/losses/categories/__init__.py
openfisca_uk/data/datasets/frs/enhanced/stages/calibration/losses/categories/demographics/__init__.py
openfisca_uk/data/datasets/frs/enhanced/stages/calibration/losses/categories/demographics/demographics.py
OpenFisca_UK-0.34.1.dist-info/LICENSE
OpenFisca_UK-0.34.1.dist-info/METADATA
OpenFisca_UK-0.34.1.dist-info/WHEEL
OpenFisca_UK-0.34.1.dist-info/entry_points.txt
OpenFisca_UK-0.34.1.dist-info/top_level.txt
OpenFisca_UK-0.34.1.dist-info/RECORD
