Metadata-Version: 2.1
Name: OpenFisca-UK
Version: 0.34.1
Summary: OpenFisca tax and benefit system for UK
Home-page: https://github.com/pslmodels/openfisca-uk
Author: PolicyEngine
Author-email: nikhil@policyengine.org
License: http://www.fsf.org/licensing/licenses/agpl-3.0.html
Keywords: benefit microsimulation social tax
Platform: UNKNOWN
Classifier: Development Status :: 5 - Production/Stable
Classifier: License :: OSI Approved :: GNU Affero General Public License v3
Classifier: Operating System :: POSIX
Classifier: Programming Language :: Python
Classifier: Topic :: Scientific/Engineering :: Information Analysis
Requires-Dist: requests (>=2.25.1)
Requires-Dist: pandas (>=1.1.4)
Requires-Dist: numpy (>=1.17.5)
Requires-Dist: pyyaml (>=5.3.1)
Requires-Dist: pytest (>=5.4.3)
Requires-Dist: OpenFisca-Core (>=35.4.1)
Requires-Dist: microdf-python (>=0.3.0)
Requires-Dist: OpenFisca-UK-Data (>=0.9.0)
Requires-Dist: OpenFisca-Tools (<1.0.0,>=0.3.0)
Requires-Dist: tqdm (>=4.59.0)
Requires-Dist: plotly (>=4.14.3)
Requires-Dist: argparse (>=1.4.0)
Requires-Dist: inquirer (>=2.7.0)
Requires-Dist: gif[plotly] (>=3.0.0)
Requires-Dist: yaml-changelog (>=0.1.5)
Requires-Dist: click (>=8.0.0)
Provides-Extra: dev
Requires-Dist: autopep8 (>=1.5) ; extra == 'dev'
Requires-Dist: flake8 (<3.8.0,>=3.5.0) ; extra == 'dev'
Requires-Dist: flake8-print ; extra == 'dev'
Requires-Dist: pycodestyle (<2.6.0,>=2.3.0) ; extra == 'dev'
Requires-Dist: tensorflow ; extra == 'dev'
Requires-Dist: streamlit ; extra == 'dev'
